{
	"quadros":[

		{
		"Código":"0",
		"Posicao":"0",
		"Nome":"Alice no País das Maravilhas",
		"Imagem": "/images/Promo/alicewonderlandpromo.jpg",
		"variavel":"promo",
		"Preço1":"44,48",
		"Preço2":"68,80",
		"Pagamento":"ou a partir de 4xR$13,90",
		"Moldura":"Em madeira de reflorestamento com pintura na cor preto fosco.",
		"Tamanho1":"40cm x 25cm(com moldura)",
		"Tamanho2":"60cm x 45cm(com moldura)",
		"Observações":"A cor do produto pode variar de acordo com as configurações do seu monitor",
		"Impressão":"Fotográfica de alta resolução com laminação fosca anti-risco",
		"Estoque1":"34 disponíveis",
		"Estoque2":"23 disponíveis"
	},

	{
		"Código":"1",
		"Posicao":"1",
		"Nome":"Alice no País das Maravilhas",
		"Imagem": "/images/filmes/alicewonderland2.jpg",
		"Preço1":"55,60",
		"Preço2":"68,80",
		"Pagamento":"ou a partir de 3xR$15,90",
		"Moldura":"Em madeira de reflorestamento com pintura na cor preto fosco.",
		"Tamanho1":"40cm x 25cm(com moldura)",
		"Tamanho2":"60cm x 45cm(com moldura)",
		"Observações":"A cor do produto pode variar de acordo com as configurações do seu monitor",
		"Impressão":"Fotográfica de alta resolução com laminação fosca anti-risco",
		"Estoque1":"43 disponíveis",
		"Estoque2":"21 disponíveis"
	},

	{
		"Código":"2",
		"Posicao":"2",
		"Nome":"Bastardos Inglórios",
		"Imagem": "/images/filmes/bastardosinglorios.jpg",
		"Preço1":"55,60",
		"Preço2":"68,80",
		"Pagamento":"ou a partir de 3xR$15,90",
		"Moldura":"Em madeira de reflorestamento com pintura na cor preto fosco.",
		"Tamanho1":"40cm x 25cm(com moldura)",
		"Tamanho2":"60cm x 45cm(com moldura)",
		"Observações":"A cor do produto pode variar de acordo com as configurações do seu monitor",
		"Impressão":"Fotográfica de alta resolução com laminação fosca anti-risco",
		"Estoque1":"46 disponíveis",
		"Estoque2":"32 disponíveis"
	},

	{
		"Código":"3",
		"Posicao":"3",
		"Nome":"Bastardos Inglórios",
		"Imagem": "/images/filmes/bastardosinglorios2.jpg",
		"Preço1":"55,60",
		"Preço2":"68,80",
		"Pagamento":"ou a partir de 3xR$15,90",
		"Moldura":"Em madeira de reflorestamento com pintura na cor preto fosco.",
		"Tamanho1":"40cm x 25cm(com moldura)",
		"Tamanho2":"60cm x 45cm(com moldura)",
		"Observações":"A cor do produto pode variar de acordo com as configurações do seu monitor",
		"Impressão":"Fotográfica de alta resolução com laminação fosca anti-risco",
		"Estoque1":"35 disponíveis",
		"Estoque2":"27 disponíveis"
	},

	{
		"Código":"4",
		"Posicao":"4",
		"Nome":"Bastardos Inglórios",
		"Imagem": "/images/filmes/bastardosinglorios3.jpg",
		"Preço1":"55,60",
		"Preço2":"68,80",
		"Pagamento":"ou a partir de 3xR$15,90",
		"Moldura":"Em madeira de reflorestamento com pintura na cor preto fosco.",
		"Tamanho1":"40cm x 25cm(com moldura)",
		"Tamanho2":"60cm x 45cm(com moldura)",
		"Observações":"A cor do produto pode variar de acordo com as configurações do seu monitor",
		"Impressão":"Fotográfica de alta resolução com laminação fosca anti-risco",
		"Estoque1":"12 disponíveis",
		"Estoque2":"9 disponíveis"
	},

	{
		"Código":"5",
		"Posicao":"5",
		"Nome":"Batman",
		"Imagem": "/images/filmes/batman.jpg",
		"Preço1":"55,60",
		"Preço2":"68,80",
		"Pagamento":"ou a partir de 3xR$15,90",
		"Moldura":"Em madeira de reflorestamento com pintura na cor preto fosco.",
		"Tamanho1":"40cm x 25cm(com moldura)",
		"Tamanho2":"60cm x 45cm(com moldura)",
		"Observações":"A cor do produto pode variar de acordo com as configurações do seu monitor",
		"Impressão":"Fotográfica de alta resolução com laminação fosca anti-risco",
		"Estoque1":"22 disponíveis",
		"Estoque2":"25 disponíveis"
	},

	{
		"Código":"6",
		"Posicao":"6",
		"Nome":"O Cisne Negro",
		"Imagem": "/images/filmes/cisnenegro.jpg",
		"Preço1":"55,60",
		"Preço2":"68,80",
		"Pagamento":"ou a partir de 3xR$15,90",
		"Moldura":"Em madeira de reflorestamento com pintura na cor preto fosco.",
		"Tamanho1":"40cm x 25cm(com moldura)",
		"Tamanho2":"60cm x 45cm(com moldura)",
		"Observações":"A cor do produto pode variar de acordo com as configurações do seu monitor",
		"Impressão":"Fotográfica de alta resolução com laminação fosca anti-risco",
		"Estoque1":"34 disponíveis",
		"Estoque2":"21 disponíveis"
	},

	{
		"Código":"7",
		"Posicao":"7",
		"Nome":"O Cisne Negro",
		"Imagem": "/images/Promo/cisnenegro2promo.jpg",
		"Preço1":"44,48",
		"Preço2":"68,80",
		"Pagamento":"ou a partir de 4xR$13,90",
		"Moldura":"Em madeira de reflorestamento com pintura na cor preto fosco.",
		"Tamanho1":"40cm x 25cm(com moldura)",
		"Tamanho2":"60cm x 45cm(com moldura)",
		"Observações":"A cor do produto pode variar de acordo com as configurações do seu monitor",
		"Impressão":"Fotográfica de alta resolução com laminação fosca anti-risco",
		"Estoque1":"11 disponíveis",
		"Estoque2":"19 disponíveis"
	},

	{
		"Código":"8",
		"Posicao":"8",
		"Nome":"Clube da Luta",
		"Imagem": "/images/filmes/clubedaluta.jpg",
		"Preço1":"55,60",
		"Preço2":"68,80",
		"Pagamento":"ou a partir de 3xR$15,90",
		"Moldura":"Em madeira de reflorestamento com pintura na cor preto fosco.",
		"Tamanho1":"40cm x 25cm(com moldura)",
		"Tamanho2":"60cm x 45cm(com moldura)",
		"Observações":"A cor do produto pode variar de acordo com as configurações do seu monitor",
		"Impressão":"Fotográfica de alta resolução com laminação fosca anti-risco",
		"Estoque1":"67 disponíveis",
		"Estoque2":"56 disponíveis"
	},

	{
		"Código":"9",
		"Posicao":"9",
		"Nome":"Clube da Luta",
		"Imagem": "/images/filmes/clubedaluta2.jpg",
		"Preço1":"55,60",
		"Preço2":"68,80",
		"Pagamento":"ou a partir de 3xR$15,90",
		"Moldura":"Em madeira de reflorestamento com pintura na cor preto fosco.",
		"Tamanho1":"40cm x 25cm(com moldura)",
		"Tamanho2":"60cm x 45cm(com moldura)",
		"Observações":"A cor do produto pode variar de acordo com as configurações do seu monitor",
		"Impressão":"Fotográfica de alta resolução com laminação fosca anti-risco",
		"Estoque1":"35 disponíveis",
		"Estoque2":"40 disponíveis"
	},

	{
		"Código":"10",
		"Posicao":"10",
		"Nome":"Django",
		"Imagem": "/images/filmes/django.jpg",
		"Preço1":"55,60",
		"Preço2":"68,80",
		"Pagamento":"ou a partir de 3xR$15,90",
		"Moldura":"Em madeira de reflorestamento com pintura na cor preto fosco.",
		"Tamanho1":"40cm x 25cm(com moldura)",
		"Tamanho2":"60cm x 45cm(com moldura)",
		"Observações":"A cor do produto pode variar de acordo com as configurações do seu monitor",
		"Impressão":"Fotográfica de alta resolução com laminação fosca anti-risco",
		"Estoque1":"32 disponíveis",
		"Estoque2":"24 disponíveis"
	},

	{
		"Código":"11",
		"Posicao":"11",
		"Nome":"Donnie Darko",
		"Imagem": "/images/filmes/donniedarko.jpg",
		"Preço1":"55,60",
		"Preço2":"68,80",
		"Pagamento":"ou a partir de 3xR$15,90",
		"Moldura":"Em madeira de reflorestamento com pintura na cor preto fosco.",
		"Tamanho1":"40cm x 25cm(com moldura)",
		"Tamanho2":"60cm x 45cm(com moldura)",
		"Observações":"A cor do produto pode variar de acordo com as configurações do seu monitor",
		"Impressão":"Fotográfica de alta resolução com laminação fosca anti-risco",
		"Estoque1":"23 disponíveis",
		"Estoque2":"54 disponíveis"
	},

	{
		"Código":"12",
		"Posicao":"12",
		"Nome":"Guardiões da Galáxia",
		"Imagem": "/images/filmes/guardioesdagalaxia.jpg",
		"Preço1":"55,60",
		"Preço2":"68,80",
		"Pagamento":"ou a partir de 3xR$15,90",
		"Moldura":"Em madeira de reflorestamento com pintura na cor preto fosco.",
		"Tamanho1":"40cm x 25cm(com moldura)",
		"Tamanho2":"60cm x 45cm(com moldura)",
		"Observações":"A cor do produto pode variar de acordo com as configurações do seu monitor",
		"Impressão":"Fotográfica de alta resolução com laminação fosca anti-risco",
		"Estoque1":"27 disponíveis",
		"Estoque2":"8 disponíveis"
	},

	{
		"Código":"13",
		"Posicao":"13",
		"Nome":"Harry Potter - Cálice de Fogo",
		"Imagem": "/images/filmes/hp1.jpg",
		"Preço1":"55,60",
		"Preço2":"68,80",
		"Pagamento":"ou a partir de 3xR$15,90",
		"Moldura":"Em madeira de reflorestamento com pintura na cor preto fosco.",
		"Tamanho1":"40cm x 25cm(com moldura)",
		"Tamanho2":"60cm x 45cm(com moldura)",
		"Observações":"A cor do produto pode variar de acordo com as configurações do seu monitor",
		"Impressão":"Fotográfica de alta resolução com laminação fosca anti-risco",
		"Estoque1":"27 disponíveis",
		"Estoque2":"16 disponíveis"
	},

	{
		"Código":"14",
		"Posicao":"14",
		"Nome":"Harry Potter - Câmara Secreta",
		"Imagem": "/images/filmes/hp2.jpg",
		"Preço1":"55,60",
		"Preço2":"68,80",
		"Pagamento":"ou a partir de 3xR$15,90",
		"Moldura":"Em madeira de reflorestamento com pintura na cor preto fosco.",
		"Tamanho1":"40cm x 25cm(com moldura)",
		"Tamanho2":"60cm x 45cm(com moldura)",
		"Observações":"A cor do produto pode variar de acordo com as configurações do seu monitor",
		"Impressão":"Fotográfica de alta resolução com laminação fosca anti-risco",
		"Estoque1":"17 disponíveis",
		"Estoque2":"16 disponíveis"
	},

	{
		"Código":"15",
		"Posicao":"15",
		"Nome":"Harry Potter - Pedra Filosofal",
		"Imagem": "/images/filmes/hp3.jpg",
		"Preço1":"55,60",
		"Preço2":"68,80",
		"Pagamento":"ou a partir de 3xR$15,90",
		"Moldura":"Em madeira de reflorestamento com pintura na cor preto fosco.",
		"Tamanho1":"40cm x 25cm(com moldura)",
		"Tamanho2":"60cm x 45cm(com moldura)",
		"Observações":"A cor do produto pode variar de acordo com as configurações do seu monitor",
		"Impressão":"Fotográfica de alta resolução com laminação fosca anti-risco",
		"Estoque1":"15 disponíveis",
		"Estoque2":"Produto Esgotado"
	},

	{
		"Código":"16",
		"Posicao":"16",
		"Nome":"Harry Potter - Ordem da Fênix",
		"Imagem": "/images/filmes/hp4.jpg",
		"Preço1":"55,60",
		"Preço2":"68,80",
		"Pagamento":"ou a partir de 3xR$15,90",
		"Moldura":"Em madeira de reflorestamento com pintura na cor preto fosco.",
		"Tamanho1":"40cm x 25cm(com moldura)",
		"Tamanho2":"60cm x 45cm(com moldura)",
		"Observações":"A cor do produto pode variar de acordo com as configurações do seu monitor",
		"Impressão":"Fotográfica de alta resolução com laminação fosca anti-risco",
		"Estoque1":"12 disponíveis",
		"Estoque2":"8 disponíveis"
	},

	{
		"Código":"17",
		"Posicao":"17",
		"Nome":"Harry Potter - Cálice de Fogo",
		"Imagem": "/images/filmes/hp5.jpg",
		"Preço1":"55,60",
		"Preço2":"68,80",
		"Pagamento":"ou a partir de 3xR$15,90",
		"Moldura":"Em madeira de reflorestamento com pintura na cor preto fosco.",
		"Tamanho1":"40cm x 25cm(com moldura)",
		"Tamanho2":"60cm x 45cm(com moldura)",
		"Observações":"A cor do produto pode variar de acordo com as configurações do seu monitor",
		"Impressão":"Fotográfica de alta resolução com laminação fosca anti-risco",
		"Estoque1":"13 disponíveis",
		"Estoque2":"Produto Esgotado"
	},

	{
		"Código":"18",
		"Posicao":"18",
		"Nome":"Harry Potter - Prisioneiro Azkaban",
		"Imagem": "/images/filmes/hp6.jpg",
		"Preço1":"55,60",
		"Preço2":"68,80",
		"Pagamento":"ou a partir de 3xR$15,90",
		"Moldura":"Em madeira de reflorestamento com pintura na cor preto fosco.",
		"Tamanho1":"40cm x 25cm(com moldura)",
		"Tamanho2":"60cm x 45cm(com moldura)",
		"Observações":"A cor do produto pode variar de acordo com as configurações do seu monitor",
		"Impressão":"Fotográfica de alta resolução com laminação fosca anti-risco",
		"Estoque1":"6 disponíveis",
		"Estoque2":"8 disponíveis"
	},

	{
		"Código":"19",
		"Posicao":"19",
		"Nome":"Harry Potter - Câmara Secreta",
		"Imagem": "/images/filmes/hp7.jpg",
		"Preço1":"55,60",
		"Preço2":"68,80",
		"Pagamento":"ou a partir de 3xR$15,90",
		"Moldura":"Em madeira de reflorestamento com pintura na cor preto fosco.",
		"Tamanho1":"40cm x 25cm(com moldura)",
		"Tamanho2":"60cm x 45cm(com moldura)",
		"Observações":"A cor do produto pode variar de acordo com as configurações do seu monitor",
		"Impressão":"Fotográfica de alta resolução com laminação fosca anti-risco",
		"Estoque1":"Produto Esgotado disponíveis",
		"Estoque2":"5 disponíveis"
	},

	{
		"Código":"20",
		"Posicao":"20",
		"Nome":"Harry Potter - Relíquias da Morte",
		"Imagem": "/images/filmes/hp8.jpg",
		"Preço1":"55,60",
		"Preço2":"68,80",
		"Pagamento":"ou a partir de 3xR$15,90",
		"Moldura":"Em madeira de reflorestamento com pintura na cor preto fosco.",
		"Tamanho1":"40cm x 25cm(com moldura)",
		"Tamanho2":"60cm x 45cm(com moldura)",
		"Observações":"A cor do produto pode variar de acordo com as configurações do seu monitor",
		"Impressão":"Fotográfica de alta resolução com laminação fosca anti-risco",
		"Estoque1":"9 disponíveis",
		"Estoque2":"3 disponíveis"
	},

	{
		"Código":"21",
		"Posicao":"21",
		"Nome":"Harry Potter - Enigma do Príncipe",
		"Imagem": "/images/filmes/hp9.jpg",
		"Preço1":"55,60",
		"Preço2":"68,80",
		"Pagamento":"ou a partir de 3xR$15,90",
		"Moldura":"Em madeira de reflorestamento com pintura na cor preto fosco.",
		"Tamanho1":"40cm x 25cm(com moldura)",
		"Tamanho2":"60cm x 45cm(com moldura)",
		"Observações":"A cor do produto pode variar de acordo com as configurações do seu monitor",
		"Impressão":"Fotográfica de alta resolução com laminação fosca anti-risco",
		"Estoque1":"6 disponíveis",
		"Estoque2":"2 disponíveis"
	},

	{
		"Código":"22",
		"Posicao":"22",
		"Nome":"Interstellar",
		"Imagem": "/images/Promo/interstellarpromo.jpg",
		"Preço1":"44,48",
		"Preço2":"68,80",
		"Pagamento":"ou a partir de 3xR$15,90",
		"Pagamento":"ou a partir de 4xR$13,90",
		"Moldura":"Em madeira de reflorestamento com pintura na cor preto fosco.",
		"Tamanho1":"40cm x 25cm(com moldura)",
		"Tamanho2":"60cm x 45cm(com moldura)",
		"Observações":"A cor do produto pode variar de acordo com as configurações do seu monitor",
		"Impressão":"Fotográfica de alta resolução com laminação fosca anti-risco",
		"Estoque1":"23 disponíveis",
		"Estoque2":"13 disponíveis"
	},

	{
		"Código":"23",
		"Posicao":"23",
		"Nome":"Interstellar",
		"Imagem": "/images/filmes/interstellar2.jpg",
		"Preço1":"55,60",
		"Preço2":"68,80",
		"Pagamento":"ou a partir de 3xR$15,90",
		"Moldura":"Em madeira de reflorestamento com pintura na cor preto fosco.",
		"Tamanho1":"40cm x 25cm(com moldura)",
		"Tamanho2":"60cm x 45cm(com moldura)",
		"Observações":":A cor do produto pode variar de acordo com as configurações do seu monitor",
		"Impressão":"Fotográfica de alta resolução com laminação fosca anti-risco",
		"Estoque1":"24 disponíveis",
		"Estoque2":"31 disponíveis"
	},

	{
		"Código":"24",
		"Posicao":"24",
		"Nome":"Kill Bill",
		"Imagem": "/images/filmes/killbill.jpg",
		"Preço1":"55,60",
		"Preço2":"68,80",
		"Pagamento":"ou a partir de 3xR$15,90",
		"Moldura":"Em madeira de reflorestamento com pintura na cor preto fosco.",
		"Tamanho1":"40cm x 25cm(com moldura)",
		"Tamanho2":"60cm x 45cm(com moldura)",
		"Observações":"A cor do produto pode variar de acordo com as configurações do seu monitor",
		"Impressão":"Fotográfica de alta resolução com laminação fosca anti-risco",
		"Estoque1":"56 disponíveis",
		"Estoque2":"45 disponíveis"
	},

	{
		"Código":"25",
		"Posicao":"25",
		"Nome":"Logan",
		"Imagem": "/images/filmes/logan.jpg",
		"Preço1":"55,60",
		"Preço2":"68,80",
		"Pagamento":"ou a partir de 3xR$15,90",
		"Moldura":"Em madeira de reflorestamento com pintura na cor preto fosco.",
		"Tamanho1":"40cm x 25cm(com moldura)",
		"Tamanho2":"60cm x 45cm(com moldura)",
		"Observações":"A cor do produto pode variar de acordo com as configurações do seu monitor",
		"Impressão":"Fotográfica de alta resolução com laminação fosca anti-risco",
		"Estoque1":"Produto Esgotado",
		"Estoque2":"Produto Esgotado"
	},

	{
		"Código":"26",
		"Posicao":"26",
		"Nome":"Mad Max",
		"Imagem": "/images/filmes/madmax.jpg",
		"Preço1":"55,60",
		"Preço2":"68,80",
		"Pagamento":"ou a partir de 3xR$15,90",
		"Moldura":"Em madeira de reflorestamento com pintura na cor preto fosco.",
		"Tamanho1":"40cm x 25cm(com moldura)",
		"Tamanho2":"60cm x 45cm(com moldura)",
		"Observações":"A cor do produto pode variar de acordo com as configurações do seu monitor",
		"Impressão":"Fotográfica de alta resolução com laminação fosca anti-risco",
		"Estoque1":"25 disponíveis",
		"Estoque2":"15 disponíveis"
	},

	{
		"Código":"27",
		"Posicao":"27",
		"Nome":"Mad Max",
		"Imagem": "/images/filmes/madmax2.jpg",
		"Preço1":"55,60",
		"Preço2":"68,80",
		"Pagamento":"ou a partir de 3xR$15,90",
		"Moldura":"Em madeira de reflorestamento com pintura na cor preto fosco.",
		"Tamanho1":"40cm x 25cm(com moldura)",
		"Tamanho2":"60cm x 45cm(com moldura)",
		"Observações":"A cor do produto pode variar de acordo com as configurações do seu monitor",
		"Impressão":"Fotográfica de alta resolução com laminação fosca anti-risco",
		"Estoque1":"23 disponíveis",
		"Estoque2":"45 disponíveis"
	},

	{
		"Código":"28",
		"Posicao":"28",
		"Nome":"O Hobbit",
		"Imagem": "/images/filmes/hobbit.jpg",
		"Preço1":"55,60",
		"Preço2":"68,80",
		"Pagamento":"ou a partir de 3xR$15,90",
		"Moldura":"Em madeira de reflorestamento com pintura na cor preto fosco.",
		"Tamanho1":"40cm x 25cm(com moldura)",
		"Tamanho2":"60cm x 45cm(com moldura)",
		"Observações":"A cor do produto pode variar de acordo com as configurações do seu monitor",
		"Impressão":"Fotográfica de alta resolução com laminação fosca anti-risco",
		"Estoque1":"2 disponíveis",
		"Estoque2":"Produto Esgotado"
	},

	{
		"Código":"29",
		"Posicao":"29",
		"Nome":"O Senhor dos Anéis",
		"Imagem": "/images/filmes/senhordosaneis.jpg",
		"Preço1":"55,60",
		"Preço2":"68,80",
		"Pagamento":"ou a partir de 3xR$15,90",
		"Moldura":"Em madeira de reflorestamento com pintura na cor preto fosco.",
		"Tamanho1":"40cm x 25cm(com moldura)",
		"Tamanho2":"60cm x 45cm(com moldura)",
		"Observações":"A cor do produto pode variar de acordo com as configurações do seu monitor",
		"Impressão":"Fotográfica de alta resolução com laminação fosca anti-risco",
		"Estoque1":"12 disponíveis",
		"Estoque2":"5 disponíveis"
	},

	{
		"Código":"30",
		"Posicao":"30",
		"Nome":"O Poderoso Chefão",
		"Imagem": "/images/filmes/poderosochefao.jpg",
		"Preço1":"55,60",
		"Preço2":"68,80",
		"Pagamento":"ou a partir de 3xR$15,90",
		"Moldura":"Em madeira de reflorestamento com pintura na cor preto fosco.",
		"Tamanho1":"40cm x 25cm(com moldura)",
		"Tamanho2":"60cm x 45cm(com moldura)",
		"Observações":"A cor do produto pode variar de acordo com as configurações do seu monitor",
		"Impressão":"Fotográfica de alta resolução com laminação fosca anti-risco",
		"Estoque1":"63 disponíveis",
		"Estoque2":"35 disponíveis"
	},


	{
		"Código":"31",
		"Posicao":"31",
		"Nome":"Robocop",
		"Imagem": "/images/filmes/robocop.jpg",
		"Preço1":"55,60",
		"Preço2":"68,80",
		"Pagamento":"ou a partir de 3xR$15,90",
		"Moldura":"Em madeira de reflorestamento com pintura na cor preto fosco.",
		"Tamanho1":"40cm x 25cm(com moldura)",
		"Tamanho2":"60cm x 45cm(com moldura)",
		"Observações":"A cor do produto pode variar de acordo com as configurações do seu monitor",
		"Impressão":"Fotográfica de alta resolução com laminação fosca anti-risco",
		"Estoque1":"21 disponíveis",
		"Estoque2":"26 disponíveis"
	},


	{
		"Código":"32",
		"Posicao":"32",
		"Nome":"Star Wars",
		"Imagem": "/images/filmes/starwars.jpg",
		"Preço1":"55,60",
		"Preço2":"68,80",
		"Pagamento":"ou a partir de 3xR$15,90",
		"Moldura":"Em madeira de reflorestamento com pintura na cor preto fosco.",
		"Tamanho1":"40cm x 25cm(com moldura)",
		"Tamanho2":"60cm x 45cm(com moldura)",
		"Observações":"A cor do produto pode variar de acordo com as configurações do seu monitor",
		"Impressão":"Fotográfica de alta resolução com laminação fosca anti-risco",
		"Estoque1":"14 disponíveis",
		"Estoque2":"25 disponíveis"
	},

	{
		"Código":"33",
		"Posicao":"33",
		"Nome":"Star Wars",
		"Imagem": "/images/filmes/starwars2.jpg",
		"Preço1":"55,60",
		"Preço2":"68,80",
		"Pagamento":"ou a partir de 3xR$15,90",
		"Moldura":"Em madeira de reflorestamento com pintura na cor preto fosco.",
		"Tamanho1":"40cm x 25cm(com moldura)",
		"Tamanho2":"60cm x 45cm(com moldura)",
		"Observações":"A cor do produto pode variar de acordo com as configurações do seu monitor",
		"Impressão":"Fotográfica de alta resolução com laminação fosca anti-risco",
		"Estoque1":"18 disponíveis",
		"Estoque2":"12 disponíveis"
	},

	{
		"Código":"34",
		"Posicao":"34",
		"Nome":"Star Wars",
		"Imagem": "/images/filmes/starwars3.jpg",
		"Preço1":"55,60",
		"Preço2":"68,80",
		"Pagamento":"ou a partir de 3xR$15,90",
		"Moldura":"Em madeira de reflorestamento com pintura na cor preto fosco.",
		"Tamanho1":"40cm x 25cm(com moldura)",
		"Tamanho2":"60cm x 45cm(com moldura)",
		"Observações":"A cor do produto pode variar de acordo com as configurações do seu monitor",
		"Impressão":"Fotográfica de alta resolução com laminação fosca anti-risco",
		"Estoque1":"14 disponíveis",
		"Estoque2":"10 disponíveis"
	},

	{
		"Código":"35",
		"Posicao":"35",
		"Nome":"Star Wars",
		"Imagem": "/images/filmes/starwars4.jpg",
		"Preço1":"55,60",
		"Preço2":"68,80",
		"Pagamento":"ou a partir de 3xR$15,90",
		"Moldura":"Em madeira de reflorestamento com pintura na cor preto fosco.",
		"Tamanho1":"40cm x 25cm(com moldura)",
		"Tamanho2":"60cm x 45cm(com moldura)",
		"Observações":"A cor do produto pode variar de acordo com as configurações do seu monitor",
		"Impressão":"Fotográfica de alta resolução com laminação fosca anti-risco",
		"Estoque1":"8 disponíveis",
		"Estoque2":"Produto Esgotado"
	},

	{
		"Código":"36",
		"Posicao":"0",
		"Nome":"AC/DC - Angus Young",
		"Imagem": "/images/Música/acdc.jpg",
		"Preço1":"55,60",
		"Preço2":"68,80",
		"Pagamento":"ou a partir de 3xR$15,90",
		"Moldura":"Em madeira de reflorestamento com pintura na cor preto fosco.",
		"Tamanho1":"40cm x 25cm(com moldura)",
		"Tamanho2":"60cm x 45cm(com moldura)",
		"Observações":"A cor do produto pode variar de acordo com as configurações do seu monitor",
		"Impressão":"Fotográfica de alta resolução com laminação fosca anti-risco",
		"Estoque1":"24 disponíveis",
		"Estoque2":"13 disponíveis"
	},

	{
		"Código":"37",
		"Posicao":"1",
		"Nome":"AC/DC",
		"Imagem": "/images/Música/acdc2.jpg",
		"Preço1":"55,60",
		"Preço2":"68,80",
		"Pagamento":"ou a partir de 3xR$15,90",
		"Moldura":"Em madeira de reflorestamento com pintura na cor preto fosco.",
		"Tamanho1":"40cm x 25cm(com moldura)",
		"Tamanho2":"60cm x 45cm(com moldura)",
		"Observações":"A cor do produto pode variar de acordo com as configurações do seu monitor",
		"Impressão":"Fotográfica de alta resolução com laminação fosca anti-risco",
		"Estoque1":"13 disponíveis",
		"Estoque2":"18 disponíveis"
	},

	{
		"Código":"38",
		"Posicao":"2",
		"Nome":"Artic Monkeys",
		"Imagem": "/images/Música/articmonkeys.jpg",
		"Preço1":"55,60",
		"Preço2":"68,80",
		"Pagamento":"ou a partir de 3xR$15,90",
		"Moldura":"Em madeira de reflorestamento com pintura na cor preto fosco.",
		"Tamanho1":"40cm x 25cm(com moldura)",
		"Tamanho2":"60cm x 45cm(com moldura)",
		"Observações":"A cor do produto pode variar de acordo com as configurações do seu monitor",
		"Impressão":"Fotográfica de alta resolução com laminação fosca anti-risco",
		"Estoque1":"10 disponíveis",
		"Estoque2":"4 disponíveis"
	},

	{
		"Código":"39",
		"Posicao":"3",
		"Nome":"The Beatles",
		"Imagem": "/images/Música/beatles.jpg",
		"Preço1":"55,60",
		"Preço2":"68,80",
		"Pagamento":"ou a partir de 3xR$15,90",
		"Moldura":"Em madeira de reflorestamento com pintura na cor preto fosco.",
		"Tamanho1":"40cm x 25cm(com moldura)",
		"Tamanho2":"60cm x 45cm(com moldura)",
		"Observações":"A cor do produto pode variar de acordo com as configurações do seu monitor",
		"Impressão":"Fotográfica de alta resolução com laminação fosca anti-risco",
		"Estoque1":"16 disponíveis",
		"Estoque2":"11 disponíveis"
	},

	{
		"Código":"40",
		"Posicao":"4",
		"Nome":"Black Sabbath",
		"Imagem": "/images/Música/blacksabbath.jpg",
		"Preço1":"55,60",
		"Preço2":"68,80",
		"Pagamento":"ou a partir de 3xR$15,90",
		"Moldura":"Em madeira de reflorestamento com pintura na cor preto fosco.",
		"Tamanho1":"40cm x 25cm(com moldura)",
		"Tamanho2":"60cm x 45cm(com moldura)",
		"Observações":"A cor do produto pode variar de acordo com as configurações do seu monitor",
		"Impressão":"Fotográfica de alta resolução com laminação fosca anti-risco",
		"Estoque1":"24 disponíveis",
		"Estoque2":"13 disponíveis"
	},

	{
		"Código":"41",
		"Posicao":"5",
		"Nome":"David Bowie",
		"Imagem": "/images/Música/davidbowie.jpg",
		"Preço1":"55,60",
		"Preço2":"68,80",
		"Pagamento":"ou a partir de 3xR$15,90",
		"Moldura":"Em madeira de reflorestamento com pintura na cor preto fosco.",
		"Tamanho1":"40cm x 25cm(com moldura)",
		"Tamanho2":"60cm x 45cm(com moldura)",
		"Observações":": cor do produto pode variar de acordo com as configurações do seu monitor",
		"Impressão":"Fotográfica de alta resolução com laminação fosca anti-risco",
		"Estoque1":"Produto Esgotado",
		"Estoque2":"Produto Esgotado"
	},

	{
		"Código":"42",
		"Posicao":"6",
		"Nome":"David Bowie",
		"Imagem": "/images/Música/davidbowie2.jpg",
		"Preço1":"55,60",
		"Preço2":"68,80",
		"Pagamento":"ou a partir de 3xR$15,90",
		"Moldura":"Em madeira de reflorestamento com pintura na cor preto fosco.",
		"Tamanho1":"40cm x 25cm(com moldura)",
		"Tamanho2":"60cm x 45cm(com moldura)",
		"Observações":"A cor do produto pode variar de acordo com as configurações do seu monitor",
		"Impressão":"Fotográfica de alta resolução com laminação fosca anti-risco",
		"Estoque1":"12 disponíveis",
		"Estoque2":"14 disponíveis"
	},

	{
		"Código":"43",
		"Posicao":"7",
		"Nome":"Led Zeppelin",
		"Imagem": "/images/Música/ledzep.jpg",
		"Preço1":"55,60",
		"Preço2":"68,80",
		"Pagamento":"ou a partir de 3xR$15,90",
		"Moldura":"Em madeira de reflorestamento com pintura na cor preto fosco.",
		"Tamanho1":"40cm x 25cm(com moldura)",
		"Tamanho2":"60cm x 45cm(com moldura)",
		"Observações":"A cor do produto pode variar de acordo com as configurações do seu monitor",
		"Impressão":"Fotográfica de alta resolução com laminação fosca anti-risco",
		"Estoque1":"12 disponíveis",
		"Estoque2":"23 disponíveis"
	},

	{
		"Código":"44",
		"Posicao":"8",
		"Nome":"Led Zeppelin",
		"Imagem": "/images/Promo/ledzep2promo.jpg",
		"Preço1":"44,48",
		"Preço2":"55,04",
		"Pagamento":"ou a partir de 4xR$13,90",
		"Moldura":"Em madeira de reflorestamento com pintura na cor preto fosco.",
		"Tamanho1":"40cm x 25cm(com moldura)",
		"Tamanho2":"60cm x 45cm(com moldura)",
		"Observações":"A cor do produto pode variar de acordo com as configurações do seu monitor",
		"Impressão":"Fotográfica de alta resolução com laminação fosca anti-risco",
		"Estoque1":"14 disponíveis",
		"Estoque2":"17 disponíveis"
	},

	{
		"Código":"45",
		"Posicao":"9",
		"Nome":"Pink Floyd",
		"Imagem": "/images/Música/pinkfloyd.jpg",
		"Preço1":"55,60",
		"Preço2":"68,80",
		"Pagamento":"ou a partir de 3xR$15,90",
		"Moldura":"Em madeira de reflorestamento com pintura na cor preto fosco.",
		"Tamanho1":"40cm x 25cm(com moldura)",
		"Tamanho2":"60cm x 45cm(com moldura)",
		"Observações":"A cor do produto pode variar de acordo com as configurações do seu monitor",
		"Impressão":"Fotográfica de alta resolução com laminação fosca anti-risco",
		"Estoque1":"6 disponíveis",
		"Estoque2":"9 disponíveis"
	},

	{
		"Código":"46",
		"Posicao":"10",
		"Nome":"Pink Floyd",
		"Imagem": "/images/Música/pinkfloyd2.jpg",
		"Preço1":"55,60",
		"Preço2":"68,80",
		"Pagamento":"ou a partir de 3xR$15,90",
		"Moldura":"Em madeira de reflorestamento com pintura na cor preto fosco.",
		"Tamanho1":"40cm x 25cm(com moldura)",
		"Tamanho2":"60cm x 45cm(com moldura)",
		"Observações":"A cor do produto pode variar de acordo com as configurações do seu monitor",
		"Impressão":"Fotográfica de alta resolução com laminação fosca anti-risco",
		"Estoque1":"12 disponíveis",
		"Estoque2":"17 disponíveis"
	},

	{
		"Código":"47",
		"Posicao":"11",
		"Nome":"Pink Floyd",
		"Imagem": "/images/Música/pinkfloyd3.jpg",
		"Preço1":"55,60",
		"Preço2":"68,80",
		"Pagamento":"ou a partir de 3xR$15,90",
		"Moldura":"Em madeira de reflorestamento com pintura na cor preto fosco.",
		"Tamanho1":"40cm x 25cm(com moldura)",
		"Tamanho2":"60cm x 45cm(com moldura)",
		"Observações":"A cor do produto pode variar de acordo com as configurações do seu monitor",
		"Impressão":"Fotográfica de alta resolução com laminação fosca anti-risco",
		"Estoque1":"3 disponíveis",
		"Estoque2":"Produto Esgotado"
	},

	{
		"Código":"48",
		"Posicao":"12",
		"Nome":"Rolling Stones",
		"Imagem": "/images/Promo/rollingstonespromo.jpg",
		"Preço1":"44,48",
		"Preço2":"55,04",
		"Pagamento":"ou a partir de 3xR$15,90",
		"Pagamento":"ou a partir de 4xR$13,90",
		"Moldura":"Em madeira de reflorestamento com pintura na cor preto fosco.",
		"Tamanho1":"40cm x 25cm(com moldura)",
		"Tamanho2":"60cm x 45cm(com moldura)",
		"Observações":"A cor do produto pode variar de acordo com as configurações do seu monitor",
		"Impressão":"Fotográfica de alta resolução com laminação fosca anti-risco",
		"Estoque1":"11 disponíveis",
		"Estoque2":"14 disponíveis"
	},

	{
		"Código":"49",
		"Posicao":"13",
		"Nome":"Sex Pistols",
		"Imagem": "/images/Música/sexpistols.jpg",
		"Preço1":"55,60",
		"Preço2":"68,80",
		"Pagamento":"ou a partir de 3xR$15,90",
		"Moldura":"Em madeira de reflorestamento com pintura na cor preto fosco.",
		"Tamanho1":"40cm x 25cm(com moldura)",
		"Tamanho2":"60cm x 45cm(com moldura)",
		"Observações":"A cor do produto pode variar de acordo com as configurações do seu monitor",
		"Impressão":"Fotográfica de alta resolução com laminação fosca anti-risco",
		"Estoque1":"20 disponíveis",
		"Estoque2":"17 disponíveis"
	},

	{
		"Código":"50",
		"Posicao":"0",
		"Nome":"Breaking Bad",
		"Imagem": "/images/Seriados/breakingbad.jpg",
		"Preço1":"55,60",
		"Preço2":"68,80",
		"Pagamento":"ou a partir de 3xR$15,90",
		"Moldura":"Em madeira de reflorestamento com pintura na cor preto fosco.",
		"Tamanho1":"40cm x 25cm(com moldura)",
		"Tamanho2":"60cm x 45cm(com moldura)",
		"Observações":"A cor do produto pode variar de acordo com as configurações do seu monitor",
		"Impressão":"Fotográfica de alta resolução com laminação fosca anti-risco",
		"Estoque1":"Produto Esgotado",
		"Estoque2":"3 disponíveis"
	},

	{
		"Código":"51",
		"Posicao":"1",
		"Nome":"Breaking Bad",
		"Imagem": "/images/Seriados/breakingbad2.jpg",
		"Preço1":"55,60",
		"Preço2":"68,80",
		"Pagamento":"ou a partir de 3xR$15,90",
		"Moldura":"Em madeira de reflorestamento com pintura na cor preto fosco.",
		"Tamanho1":"40cm x 25cm(com moldura)",
		"Tamanho2":"60cm x 45cm(com moldura)",
		"Observações":"A cor do produto pode variar de acordo com as configurações do seu monitor",
		"Impressão":"Fotográfica de alta resolução com laminação fosca anti-risco",
		"Estoque1":"9 disponíveis",
		"Estoque2":"3 disponíveis"
	},

	{
		"Código":"52",
		"Posicao":"2",
		"Nome":"Breaking Bad",
		"Imagem": "/images/Seriados/breakingbad3.jpg",
		"Preço1":"55,60",
		"Preço2":"68,80",
		"Pagamento":"ou a partir de 3xR$15,90",
		"Moldura":"Em madeira de reflorestamento com pintura na cor preto fosco.",
		"Tamanho1":"40cm x 25cm(com moldura)",
		"Tamanho2":"60cm x 45cm(com moldura)",
		"Observações":"A cor do produto pode variar de acordo com as configurações do seu monitor",
		"Impressão":"Fotográfica de alta resolução com laminação fosca anti-risco",
		"Estoque1":"Produto Esgotado",
		"Estoque2":"Produto Esgotado"
	},

	{
		"Código":"53",
		"Posicao":"3",
		"Nome":"Breaking Bad",
		"Imagem": "/images/Seriados/breakingbad4.jpg",
		"Preço1":"55,60",
		"Preço2":"68,80",
		"Pagamento":"ou a partir de 3xR$15,90",
		"Moldura":"Em madeira de reflorestamento com pintura na cor preto fosco.",
		"Tamanho1":"40cm x 25cm(com moldura)",
		"Tamanho2":"60cm x 45cm(com moldura)",
		"Observações":"A cor do produto pode variar de acordo com as configurações do seu monitor",
		"Impressão":"Fotográfica de alta resolução com laminação fosca anti-risco",
		"Estoque1":"14 disponíveis",
		"Estoque2":"11 disponíveis"
	},

	{
		"Código":"54",
		"Posicao":"4",
		"Nome":"Dexter",
		"Imagem": "/images/Seriados/dexter.jpg",
		"Preço1":"55,60",
		"Preço2":"68,80",
		"Pagamento":"ou a partir de 3xR$15,90",
		"Moldura":"Em madeira de reflorestamento com pintura na cor preto fosco.",
		"Tamanho1":"40cm x 25cm(com moldura)",
		"Tamanho2":"60cm x 45cm(com moldura)",
		"Observações":"A cor do produto pode variar de acordo com as configurações do seu monitor",
		"Impressão":"Fotográfica de alta resolução com laminação fosca anti-risco",
		"Estoque1":"12 disponíveis",
		"Estoque2":"23 disponíveis"
	},

	{
		"Código":"55",
		"Posicao":"5",
		"Nome":"Doctor Who",
		"Imagem": "/images/Promo/doctorwhopromo.jpg",
		"Preço1":"44,48",
		"Preço2":"55,04",
		"Pagamento":"ou a partir de 4xR$13,90",
		"Moldura":"Em madeira de reflorestamento com pintura na cor preto fosco.",
		"Tamanho1":"40cm x 25cm(com moldura)",
		"Tamanho2":"60cm x 45cm(com moldura)",
		"Observações":"A cor do produto pode variar de acordo com as configurações do seu monitor",
		"Impressão":"Fotográfica de alta resolução com laminação fosca anti-risco",
		"Estoque1":"2 disponíveis",
		"Estoque2":"6 disponíveis"
	},

	{
		"Código":"56",
		"Posicao":"6",
		"Nome":"Doctor Who",
		"Imagem": "/images/Seriados/doctorwho2.jpg",
		"Preço1":"55,60",
		"Preço2":"68,80",
		"Pagamento":"ou a partir de 3xR$15,90",
		"Moldura":"Em madeira de reflorestamento com pintura na cor preto fosco.",
		"Tamanho1":"40cm x 25cm(com moldura)",
		"Tamanho2":"60cm x 45cm(com moldura)",
		"Observações":"A cor do produto pode variar de acordo com as configurações do seu monitor",
		"Impressão":"Fotográfica de alta resolução com laminação fosca anti-risco",
		"Estoque1":"13 disponíveis",
		"Estoque2":"9 disponíveis"
	},

	{
		"Código":"57",
		"Posicao":"7",
		"Nome":"Game Of Thrones",
		"Imagem": "/images/Seriados/got.jpg",
		"Preço1":"55,60",
		"Preço2":"68,80",
		"Pagamento":"ou a partir de 3xR$15,90",
		"Moldura":"Em madeira de reflorestamento com pintura na cor preto fosco.",
		"Tamanho1":"40cm x 25cm(com moldura)",
		"Tamanho2":"60cm x 45cm(com moldura)",
		"Observações":"A cor do produto pode variar de acordo com as configurações do seu monitor",
		"Impressão":"Fotográfica de alta resolução com laminação fosca anti-risco",
		"Estoque1":"23 disponíveis",
		"Estoque2":"18 disponíveis"
	},

	{
		"Código":"58",
		"Posicao":"8",
		"Nome":"Game Of Thrones",
		"Imagem": "/images/Seriados/got2.jpg",
		"Preço1":"55,60",
		"Preço2":"68,80",
		"Pagamento":"ou a partir de 3xR$15,90",
		"Moldura":"Em madeira de reflorestamento com pintura na cor preto fosco.",
		"Tamanho1":"40cm x 25cm(com moldura)",
		"Tamanho2":"60cm x 45cm(com moldura)",
		"Observações":"A cor do produto pode variar de acordo com as configurações do seu monitor",
		"Impressão":"Fotográfica de alta resolução com laminação fosca anti-risco",
		"Estoque1":"5 disponíveis",
		"Estoque2":"8 disponíveis"
	},

	{
		"Código":"59",
		"Posicao":"9",
		"Nome":"Game Of Thrones",
		"Imagem": "/images/Seriados/got3.jpg",
		"Preço1":"55,60",
		"Preço2":"68,80",
		"Pagamento":"ou a partir de 3xR$15,90",
		"Moldura":"Em madeira de reflorestamento com pintura na cor preto fosco.",
		"Tamanho1":"40cm x 25cm(com moldura)",
		"Tamanho2":"60cm x 45cm(com moldura)",
		"Observações":"A cor do produto pode variar de acordo com as configurações do seu monitor",
		"Impressão":"Fotográfica de alta resolução com laminação fosca anti-risco",
		"Estoque1":"10 disponíveis",
		"Estoque2":"14 disponíveis"
	},

	{
		"Código":"60",
		"Posicao":"10",
		"Nome":"Game Of Thrones",
		"Imagem": "/images/Seriados/got4.jpg",
		"Preço1":"55,60",
		"Preço2":"68,80",
		"Pagamento":"ou a partir de 3xR$15,90",
		"Moldura":"Em madeira de reflorestamento com pintura na cor preto fosco.",
		"Tamanho1":"40cm x 25cm(com moldura)",
		"Tamanho2":"60cm x 45cm(com moldura)",
		"Observações":"A cor do produto pode variar de acordo com as configurações do seu monitor",
		"Impressão":"Fotográfica de alta resolução com laminação fosca anti-risco",
		"Estoque1":"Produto Esgotado",
		"Estoque2":"Produto Esgotado"
	},

	{
		"Código":"61",
		"Posicao":"11",
		"Nome":"How I Met You Mother",
		"Imagem": "/images/Seriados/howimet.jpg",
		"Preço1":"55,60",
		"Preço2":"68,80",
		"Pagamento":"ou a partir de 3xR$15,90",
		"Moldura":"Em madeira de reflorestamento com pintura na cor preto fosco.",
		"Tamanho1":"40cm x 25cm(com moldura)",
		"Tamanho2":"60cm x 45cm(com moldura)",
		"Observações":"A cor do produto pode variar de acordo com as configurações do seu monitor",
		"Impressão":"Fotográfica de alta resolução com laminação fosca anti-risco",
		"Estoque1":"13 disponíveis",
		"Estoque2":"10 disponíveis"
	},

	{
		"Código":"62",
		"Posicao":"12",
		"Nome":"How I Met You Mother",
		"Imagem": "/images/Seriados/howimet2.jpg",
		"Preço1":"55,60",
		"Preço2":"68,80",
		"Pagamento":"ou a partir de 3xR$15,90",
		"Moldura":"Em madeira de reflorestamento com pintura na cor preto fosco.",
		"Tamanho1":"40cm x 25cm(com moldura)",
		"Tamanho2":"60cm x 45cm(com moldura)",
		"Observações":"A cor do produto pode variar de acordo com as configurações do seu monitor",
		"Impressão":"Fotográfica de alta resolução com laminação fosca anti-risco",
		"Estoque1":"10 disponíveis",
		"Estoque2":"11 disponíveis"
	},

	{
		"Código":"63",
		"Posicao":"13",
		"Nome":"Stranger Things",
		"Imagem": "/images/Seriados/stranger.jpg",
		"Preço1":"55,60",
		"Preço2":"68,80",
		"Pagamento":"ou a partir de 3xR$15,90",
		"Moldura":"Em madeira de reflorestamento com pintura na cor preto fosco.",
		"Tamanho1":"40cm x 25cm(com moldura)",
		"Tamanho2":"60cm x 45cm(com moldura)",
		"Observações":"A cor do produto pode variar de acordo com as configurações do seu monitor",
		"Impressão":"Fotográfica de alta resolução com laminação fosca anti-risco",
		"Estoque1":"3 disponíveis",
		"Estoque2":"6 disponíveis"
	},

	{
		"Código":"64",
		"Posicao":"14",
		"Nome":"Stranger Things",
		"Imagem": "/images/Seriados/stranger2.jpg",
		"Preço1":"55,60",
		"Preço2":"68,80",
		"Pagamento":"ou a partir de 3xR$15,90",
		"Moldura":"Em madeira de reflorestamento com pintura na cor preto fosco.",
		"Tamanho1":"40cm x 25cm(com moldura)",
		"Tamanho2":"60cm x 45cm(com moldura)",
		"Observações":"A cor do produto pode variar de acordo com as configurações do seu monitor",
		"Impressão":"Fotográfica de alta resolução com laminação fosca anti-risco",
		"Estoque1":"10 disponíveis",
		"Estoque2":"Produto Esgotado"
	},

	{
		"Código":"65",
		"Posicao":"15",
		"Nome":"Supernatural",
		"Imagem": "/images/Seriados/supernatural.jpg",
		"Preço1":"55,60",
		"Preço2":"68,80",
		"Pagamento":"ou a partir de 3xR$15,90",
		"Moldura":"Em madeira de reflorestamento com pintura na cor preto fosco.",
		"Tamanho1":"40cm x 25cm(com moldura)",
		"Tamanho2":"60cm x 45cm(com moldura)",
		"Observações":"A cor do produto pode variar de acordo com as configurações do seu monitor",
		"Impressão":"Fotográfica de alta resolução com laminação fosca anti-risco",
		"Estoque1":"12 disponíveis",
		"Estoque2":"9 disponíveis"
	},

	{
		"Código":"66",
		"Posicao":"0",
		"Nome":"Aladdin",
		"Imagem": "/images/Promo/aladdinpromo.jpg",
		"Preço1":"44,48",
		"Preço2":"68,80",
		"Pagamento":"ou a partir de 4xR$13,90",
		"Moldura":"Em madeira de reflorestamento com pintura na cor preto fosco.",
		"Tamanho1":"40cm x 25cm(com moldura)",
		"Tamanho2":"60cm x 45cm(com moldura)",
		"Observações":"A cor do produto pode variar de acordo com as configurações do seu monitor",
		"Impressão":"Fotográfica de alta resolução com laminação fosca anti-risco",
		"Estoque1":"30 disponíveis",
		"Estoque2":"24 disponíveis"
	},


	{
		"Código":"67",
		"Posicao":"1",
		"Nome":"Bambi",
		"Imagem": "/images/Desenhos/bambi.jpg",
		"Preço1":"55,60",
		"Preço2":"68,80",
		"Pagamento":"ou a partir de 3xR$15,90",
		"Moldura":"Em madeira de reflorestamento com pintura na cor preto fosco.",
		"Tamanho1":"40cm x 25cm(com moldura)",
		"Tamanho2":"60cm x 45cm(com moldura)",
		"Observações":"A cor do produto pode variar de acordo com as configurações do seu monitor",
		"Impressão":"Fotográfica de alta resolução com laminação fosca anti-risco",
		"Estoque1":"20 disponíveis",
		"Estoque2":"16 disponíveis"
	},

	{
		"Código":"68",
		"Posicao":"2",
		"Nome":"Dragon Ball",
		"Imagem": "/images/Desenhos/dragonball.jpg",
		"Preço1":"55,60",
		"Preço2":"68,80",
		"Pagamento":"ou a partir de 3xR$15,90",
		"Moldura":"Em madeira de reflorestamento com pintura na cor preto fosco.",
		"Tamanho1":"40cm x 25cm(com moldura)",
		"Tamanho2":"60cm x 45cm(com moldura)",
		"Observações":"A cor do produto pode variar de acordo com as configurações do seu monitor",
		"Impressão":"Fotográfica de alta resolução com laminação fosca anti-risco",
		"Estoque1":"15 disponíveis",
		"Estoque2":"8 disponíveis"
	},

	{
		"Código":"69",
		"Posicao":"3",
		"Nome":"Dragon Ball",
		"Imagem": "/images/Promo/dragonball2promo.jpg",
		"Preço1":"44,48",
		"Preço2":"55,04",
		"Pagamento":"ou a partir de 4xR$13,90",
		"Moldura":"Em madeira de reflorestamento com pintura na cor preto fosco.",
		"Tamanho1":"40cm x 25cm(com moldura)",
		"Tamanho2":"60cm x 45cm(com moldura)",
		"Observações":"A cor do produto pode variar de acordo com as configurações do seu monitor",
		"Impressão":"Fotográfica de alta resolução com laminação fosca anti-risco",
		"Estoque1":"6 disponíveis",
		"Estoque2":"7 disponíveis"
	},

	{
		"Código":"70",
		"Posicao":"4",
		"Nome":"Hora de Aventura",
		"Imagem": "/images/Desenhos/adventuretime.jpg",
		"Preço1":"55,60",
		"Preço2":"68,80",
		"Pagamento":"ou a partir de 3xR$15,90",
		"Moldura":"Em madeira de reflorestamento com pintura na cor preto fosco.",
		"Tamanho1":"40cm x 25cm(com moldura)",
		"Tamanho2":"60cm x 45cm(com moldura)",
		"Observações":"A cor do produto pode variar de acordo com as configurações do seu monitor",
		"Impressão":"Fotográfica de alta resolução com laminação fosca anti-risco",
		"Estoque1":"23 disponíveis",
		"Estoque2":"14 disponíveis"
	},

	{
		"Código":"71",
		"Posicao":"5",
		"Nome":"Toy Story",
		"Imagem": "/images/Desenhos/toystory.jpg",
		"Preço1":"55,60",
		"Preço2":"68,80",
		"Pagamento":"ou a partir de 3xR$15,90",
		"Moldura":"Em madeira de reflorestamento com pintura na cor preto fosco.",
		"Tamanho1":"40cm x 25cm(com moldura)",
		"Tamanho2":"60cm x 45cm(com moldura)",
		"Observações":"A cor do produto pode variar de acordo com as configurações do seu monitor",
		"Impressão":"Fotográfica de alta resolução com laminação fosca anti-risco",
		"Estoque1":"12 disponíveis",
		"Estoque2":"20 disponíveis"
	},

	{
		"Código":"85",
		"Posicao":"0",
		"Nome":"Clube da Luta",
		"Imagem": "/images/filmes/clubedaluta.jpg",
		"Preço1":"55,60",
		"Preço2":"68,80",
		"Moldura":"Em madeira de reflorestamento com pintura na cor preto fosco.",
		"Tamanho1":"40cm x 25cm(com moldura)",
		"Tamanho2":"60cm x 45cm(com moldura)",
		"Observações":"A cor do produto pode variar de acordo com as configurações do seu monitor",
		"Impressão":"Fotográfica de alta resolução com laminação fosca anti-risco",
		"Estoque1":"67 disponíveis",
		"Estoque2":"56 disponíveis"
	},

	{
		"Código":"86",
		"Posicao":"1",
		"Nome":"Logan",
		"Imagem": "/images/filmes/logan.jpg",
		"Preço1":"55,60",
		"Preço2":"68,80",
		"Moldura":"Em madeira de reflorestamento com pintura na cor preto fosco.",
		"Tamanho1":"40cm x 25cm(com moldura)",
		"Tamanho2":"60cm x 45cm(com moldura)",
		"Observações":"A cor do produto pode variar de acordo com as configurações do seu monitor",
		"Impressão":"Fotográfica de alta resolução com laminação fosca anti-risco",
		"Estoque1":"Produto Esgotado",
		"Estoque2":"Produto Esgotado"
	},

	{
		"Código":"87",
		"Posicao":"2",
		"Nome":"Star Wars",
		"Imagem": "/images/filmes/starwars4.jpg",
		"Preço1":"55,60",
		"Preço2":"68,80",
		"Moldura":"Em madeira de reflorestamento com pintura na cor preto fosco.",
		"Tamanho1":"40cm x 25cm(com moldura)",
		"Tamanho2":"60cm x 45cm(com moldura)",
		"Observações":"A cor do produto pode variar de acordo com as configurações do seu monitor",
		"Impressão":"Fotográfica de alta resolução com laminação fosca anti-risco",
		"Estoque1":"8 disponíveis",
		"Estoque2":"Produto Esgotado"
	},

	{
		"Código":"88",
		"Posicao":"3",
		"Nome":"Artic Monkeys",
		"Imagem": "/images/música/articmonkeys.jpg",
		"Preço1":"55,60",
		"Preço2":"68,80",
		"Moldura":"Em madeira de reflorestamento com pintura na cor preto fosco.",
		"Tamanho1":"40cm x 25cm(com moldura)",
		"Tamanho2":"60cm x 45cm(com moldura)",
		"Observações":"A cor do produto pode variar de acordo com as configurações do seu monitor",
		"Impressão":"Fotográfica de alta resolução com laminação fosca anti-risco",
		"Estoque1":"10 disponíveis",
		"Estoque2":"4 disponíveis"
	},

	{
		"Código":"89",
		"Posicao":"4",
		"Nome":"Pink Floyd",
		"Imagem": "/images/música/pinkfloyd3.jpg",
		"Preço1":"55,60",
		"Preço2":"68,80",
		"Moldura":"Em madeira de reflorestamento com pintura na cor preto fosco.",
		"Tamanho1":"40cm x 25cm(com moldura)",
		"Tamanho2":"60cm x 45cm(com moldura)",
		"Observações":"A cor do produto pode variar de acordo com as configurações do seu monitor",
		"Impressão":"Fotográfica de alta resolução com laminação fosca anti-risco",
		"Estoque1":"3 disponíveis",
		"Estoque2":"Produto Esgotado"
	},

	{
		"Código":"90",
		"Posicao":"5",
		"Nome":"Stranger Things",
		"Imagem": "/images/seriados/stranger2.jpg",
		"Preço1":"55,60",
		"Preço2":"68,80",
		"Moldura":"Em madeira de reflorestamento com pintura na cor preto fosco.",
		"Tamanho1":"40cm x 25cm(com moldura)",
		"Tamanho2":"60cm x 45cm(com moldura)",
		"Observações":"A cor do produto pode variar de acordo com as configurações do seu monitor",
		"Impressão":"Fotográfica de alta resolução com laminação fosca anti-risco",
		"Estoque1":"10 disponíveis",
		"Estoque2":"Produto Esgotado"
	}

	],


	"canecas":[
		{
		"Código":"72",
		"Posicao":"0",
		"Nome":"Alice no País das Maravilhas",
		"Imagem": "/images/Canecas/alice.jpg",
		"Preço1":"28,50",
		"Pagamento":"ou a partir de 2xR$14,25",
		"Material":"Cerâmica",
		"Capacidade":"300ml",
		"Observações":"A cor do produto pode variar de acordo com as configurações do seu monitor",
		"Dimensões com Embalagem":"12x12x12cm",
		"Estoque1":"30 disponíveis"
	},

	{
		"Código":"73",
		"Posicao":"1",
		"Nome":"Bastardos Inglórios",
		"Imagem": "/images/Canecas/bastardos.jpg",
		"Preço1":"28,50",
		"Pagamento":"ou a partir de 2xR$14,25",
		"Material":"Cerâmica",
		"Capacidade":"300ml",
		"Observações":"A cor do produto pode variar de acordo com as configurações do seu monitor",
		"Dimensões com Embalagem":"12x12x12cm",
		"Estoque1":"24 disponíveis"
	},

	{
		"Código":"74",
		"Posicao":"2",
		"Nome":"Batman",
		"Imagem": "/images/Canecas/batman.jpg",
		"Preço1":"28,50",
		"Pagamento":"ou a partir de 2xR$14,25",
		"Material":"Cerâmica",
		"Capacidade":"300ml",
		"Observações":"A cor do produto pode variar de acordo com as configurações do seu monitor",
		"Dimensões com Embalagem":"12x12x12cm",
		"Estoque1":"19 disponíveis"
	},

	{
		"Código":"75",
		"Posicao":"3",
		"Nome":"Cazuza",
		"Imagem": "/images/Canecas/cazuza.jpg",
		"Preço1":"28,50",
		"Pagamento":"ou a partir de 2xR$14,25",
		"Material":"Cerâmica",
		"Capacidade":"300ml",
		"Observações":"A cor do produto pode variar de acordo com as configurações do seu monitor",
		"Dimensões com Embalagem":"12x12x12cm",
		"Estoque1":"49 disponíveis"
	},

	{
		"Código":"76",
		"Posicao":"4",
		"Nome":"Clube da Luta",
		"Imagem": "/images/Canecas/clubedaluta.jpg",
		"Preço1":"28,50",
		"Pagamento":"ou a partir de 2xR$14,25",
		"Material":"Cerâmica",
		"Capacidade":"300ml",
		"Observações":"A cor do produto pode variar de acordo com as configurações do seu monitor",
		"Dimensões com Embalagem":"12x12x12cm",
		"Estoque1":"10 disponíveis"
	},

	{
		"Código":"77",
		"Posicao":"5",
		"Nome":"David Bowie",
		"Imagem": "/images/Canecas/davidbowie.jpg",
		"Preço1":"28,50",
		"Pagamento":"ou a partir de 2xR$14,25",
		"Material":"Cerâmica",
		"Capacidade":"300ml",
		"Observações":"A cor do produto pode variar de acordo com as configurações do seu monitor",
		"Dimensões com Embalagem":"12x12x12cm",
		"Estoque1":"4 disponíveis"
	},

	{
		"Código":"78",
		"Posicao":"6",
		"Nome":"Dexter",
		"Preço1":"28,50",
		"Imagem": "/images/Canecas/dexter.jpg",
		"Pagamento":"ou a partir de 2xR$14,25",
		"Material":"Cerâmica",
		"Capacidade":"300ml",
		"Observações":"A cor do produto pode variar de acordo com as configurações do seu monitor",
		"Dimensões com Embalagem":"12x12x12cm",
		"Estoque1":"20 disponíveis"
	},

	{
		"Código":"79",
		"Posicao":"7",
		"Nome":"Harry Potter",
		"Imagem": "/images/Canecas/hp.jpg",
		"Preço1":"28,50",
		"Pagamento":"ou a partir de 2xR$14,25",
		"Material":"Cerâmica",
		"Capacidade":"300ml",
		"Observações":"A cor do produto pode variar de acordo com as configurações do seu monitor",
		"Dimensões com Embalagem":"12x12x12cm",
		"Estoque1":"12 disponíveis"
	},

	{
		"Código":"80",
		"Posicao":"8",
		"Nome":"O Hobbit",
		"Imagem": "/images/Canecas/hobbit.jpg",
		"Preço1":"28,50",
		"Pagamento":"ou a partir de 2xR$14,25",
		"Material":"Cerâmica",
		"Capacidade":"300ml",
		"Observações":"A cor do produto pode variar de acordo com as configurações do seu monitor",
		"Dimensões com Embalagem":"12x12x12cm",
		"Estoque1":"9 disponíveis"
	},

	{
		"Código":"81",
		"Posicao":"9",
		"Nome":"Pink Floyd",
		"Imagem": "/images/Canecas/pf.jpg",
		"Preço1":"28,50",
		"Pagamento":"ou a partir de 2xR$14,25",
		"Material":"Cerâmica",
		"Capacidade":"300ml",
		"Observações":"A cor do produto pode variar de acordo com as configurações do seu monitor",
		"Dimensões com Embalagem":"12x12x12cm",
		"Estoque1":"5 disponíveis"
	},

	{
		"Código":"82",
		"Posicao":"10",
		"Nome":"Star Trek",
		"Imagem": "/images/Canecas/startrek.jpg",
		"Preço1":"28,50",
		"Pagamento":"ou a partir de 2xR$14,25",
		"Material":"Cerâmica",
		"Capacidade":"300ml",
		"Observações":"A cor do produto pode variar de acordo com as configurações do seu monitor",
		"Dimensões com Embalagem":"12x12x12cm",
		"Estoque1":"14 disponíveis"
	},

	{
		"Código":"83",
		"Posicao":"11",
		"Nome":"Star Wars",
		"Imagem": "/images/Canecas/starwars.jpg",
		"Preço1":"28,50",
		"Pagamento":"ou a partir de 2xR$14,25",
		"Material":"Cerâmica",
		"Capacidade":"300ml",
		"Observações":"A cor do produto pode variar de acordo com as configurações do seu monitor",
		"Dimensões com Embalagem":"12x12x12cm",
		"Estoque1":"14 disponíveis"
	},

	{
		"Código":"84",
		"Posicao":"12",
		"Nome":"Stranger Things",
		"Imagem": "/images/Canecas/stranger.jpg",
		"Preço1":"28,50",
		"Pagamento":"ou a partir de 2xR$14,25",
		"Material":"Cerâmica",
		"Capacidade":"300ml",
		"Observações":"A cor do produto pode variar de acordo com as configurações do seu monitor",
		"Dimensões com Embalagem":"12x12x12cm",
		"Estoque1":"8 disponíveis"
	}
]
}